HMAP/HMAP.py
HMAP/HMAPSC.py
HMAP/HMAPSCMO.py
HMAP/HMAP_bk.py
HMAP/HMAP_test.py
HMAP/__init__.py
HMAP/atac/__init__.py
HMAP/atac/utils.py
HMAP/graph/__init__.py
HMAP/graph/graph.py
HMAP/utils/__init__.py
HMAP/utils/custom_mlp.py
HMAP/utils/utils.py
hmap_tool-1.0.9.dist-info/licenses/LICENSE
hmap_tool-1.0.9.dist-info/METADATA
hmap_tool-1.0.9.dist-info/WHEEL
hmap_tool-1.0.9.dist-info/entry_points.txt
hmap_tool-1.0.9.dist-info/top_level.txt
hmap_tool-1.0.9.dist-info/RECORD
