Metadata-Version: 2.4
Name: HMAP-tool
Version: 1.0.9
Summary: Hierarchical Manifold Approximation and Projection for Single Cell Data
Home-page: https://github.com/ZengFLab/HMAP
Author: Feng Zeng
Author-email: zengfeng@xmu.edu.cn
Classifier: Programming Language :: Python :: 3
Classifier: License :: OSI Approved :: MIT License
Classifier: Operating System :: OS Independent
Requires-Python: >=3.10
License-File: LICENSE
Requires-Dist: dill==0.3.8
Requires-Dist: scanpy
Requires-Dist: datatable
Requires-Dist: scipy
Requires-Dist: numpy
Requires-Dist: scikit-learn
Requires-Dist: pandas
Requires-Dist: pyro-ppl
Requires-Dist: leidenalg
Requires-Dist: python-igraph
Requires-Dist: networkx
Requires-Dist: matplotlib
Requires-Dist: seaborn
Requires-Dist: fa2-modified
Dynamic: author
Dynamic: author-email
Dynamic: classifier
Dynamic: description
Dynamic: description-content-type
Dynamic: home-page
Dynamic: license-file
Dynamic: requires-dist
Dynamic: requires-python
Dynamic: summary
